starfinder-1.1.0.dist-info/METADATA
starfinder-1.1.0.dist-info/WHEEL
starfinder-1.1.0.dist-info/licenses/LICENSE
starfinder.libs/libgcc_s-5b5488a6.so.1
starfinder/__init__.py
starfinder/starfinder.cpython-39-arm-linux-gnueabihf.so
starfinder-1.1.0.dist-info/RECORD
