Metadata-Version: 2.3
Name: starfinder
Version: 1.1.0
Classifier: Programming Language :: Rust
Classifier: Programming Language :: Python :: Implementation :: CPython
Classifier: Programming Language :: Python :: Implementation :: PyPy
Classifier: Operating System :: OS Independent
License-File: LICENSE
Summary: Generate images of the sky w/ accurate stars for star sensor simulation
Home-Page: https://github.com/djmango/starfinder
Author-email: Sulaiman Khan Ghori <sulaiman.ghori@outlook.com>, Layton Miller <layton.r.miller@gmail.com>
Requires-Python: >=3.8
Project-URL: Homepage, https://github.com/djmango/starfinder
Project-URL: Issues, https://github.com/djmango/starfinder/issues
